CHANGES.txt
README.txt
bootstrap.py
buildout.cfg
setup.py
src/zope/__init__.py
src/zope.app.dtmlpage.egg-info/PKG-INFO
src/zope.app.dtmlpage.egg-info/SOURCES.txt
src/zope.app.dtmlpage.egg-info/dependency_links.txt
src/zope.app.dtmlpage.egg-info/namespace_packages.txt
src/zope.app.dtmlpage.egg-info/not-zip-safe
src/zope.app.dtmlpage.egg-info/requires.txt
src/zope.app.dtmlpage.egg-info/top_level.txt
src/zope/app/__init__.py
src/zope/app/dtmlpage/DEPENDENCIES.cfg
src/zope/app/dtmlpage/PACKAGE.cfg
src/zope/app/dtmlpage/SETUP.cfg
src/zope/app/dtmlpage/__init__.py
src/zope/app/dtmlpage/browser.py
src/zope/app/dtmlpage/configure.zcml
src/zope/app/dtmlpage/dtml.gif
src/zope/app/dtmlpage/dtmlpage.py
src/zope/app/dtmlpage/ftesting.zcml
src/zope/app/dtmlpage/interfaces.py
src/zope/app/dtmlpage/testing.py
src/zope/app/dtmlpage/url.txt
src/zope/app/dtmlpage/zope.app.dtmlpage-configure.zcml
src/zope/app/dtmlpage/tests/__init__.py
src/zope/app/dtmlpage/tests/test_dtmlpage.py
src/zope/app/dtmlpage/tests/test_dtmlpageeval.py
src/zope/app/dtmlpage/tests/test_functional.py